{
  "mcpServers": {
    "shadcn": {
      "command": "npx",
      "args": [
        "shadcn@latest",
        "mcp"
      ]
    },
    "sequential-thinking": {
      "type": "stdio",
      "command": "npx",
      "args": ["-y", "@modelcontextprotocol/server-sequential-thinking"],
      "env": {}
    },
    "github": {
      "type": "stdio",
      "command": "npx",
      "args": ["-y", "@modelcontextprotocol/server-github"],
      "env": {
        "GITHUB_PERSONAL_ACCESS_TOKEN": "${GITHUB_PERSONAL_ACCESS_TOKEN}"
      }
    },
    "fetch": {
      "type": "stdio",
      "command": "uvx",
      "args": ["mcp-server-fetch"],
      "env": {}
    },
    "playwright": {
      "type": "stdio",
      "command": "npx",
      "args": ["-y", "@playwright/mcp@latest"],
      "env": {}
    }
  }
}
